{
  "0": "Business Domain & Catalog Data",
  "1": "Inventory Import (Existencias)",
  "2": "Routes, Auth & Upload Middleware",
  "3": "Sales / Pedidos Controller",
  "4": "Frontend Dependencies",
  "5": "Solicitudes & Web Price Search",
  "6": "Customer Quote & PDF",
  "7": "Backend Dependencies",
  "8": "React Pages (Lists & Forms)",
  "9": "Products Controller & AI Matcher",
  "10": "Support Catalogs (Categorias/Familias)",
  "11": "Layout, Auth Store & Users UI",
  "12": "PRONAMAC Catalog Import CLI",
  "13": "Clientes Controller",
  "14": "SSH Deploy Script",
  "15": "Proveedores Controller",
  "16": "DB Migrations & Connection Pool",
  "17": "Usuarios Controller",
  "18": "Catalog Import CLI",
  "19": "SKU Matcher Engine",
  "20": "Supplier Quote Pricing",
  "21": "Authentication (Login / JWT)",
  "22": "App Bootstrap & Env Validation",
  "23": "Products & Catalog UI",
  "24": "Supplier Catalog & Product Picker UI",
  "25": "INNOVACOM Brand Assets",
  "26": "Almacenes / Ubicaciones Controller",
  "27": "Inventory Movements UI",
  "28": "Pedido Detail UI",
  "29": "PDF Parser (AI)",
  "30": "Migration v9",
  "31": "Debian Deploy Script",
  "32": "Excel Parser",
  "33": "Admin Seed",
  "34": "Inventory Seed",
  "35": "Cotizaciones List UI",
  "36": "Cotizacion Detail UI",
  "37": "Apache Fix Script",
  "38": "MySQL Fix Script",
  "39": "Existencias UI",
  "40": "Dashboard UI",
  "41": "Price Comparator UI",
  "42": "Proveedores List UI",
  "43": "Migration v10",
  "44": "Migration v2",
  "45": "Migration v6",
  "46": "Migration v7",
  "47": "Nueva Cotizacion UI",
  "48": "Apache Fix Script 2",
  "49": "Migration Runner",
  "50": "deploy_inv1.sh script",
  "51": "deploy_iva2.sh script",
  "52": "deploy_iva.sh script",
  "53": "deploy.sh script",
  "54": "check_server.py",
  "55": "EscBash()",
  "56": "fix_apache.py",
  "57": "sw.js",
  "58": "run_migration_v3.py",
  "59": "run_migration_v4.py",
  "60": "run_migration_v5.py",
  "61": "run_migration_v6.py",
  "62": "set_api_key.py",
  "63": "main.jsx",
  "64": "ecosystem.config.js",
  "65": "check_mysql.py",
  "66": "postcss.config.js",
  "67": "tailwind.config.js",
  "68": "vite.config.js",
  "69": "Community 69",
  "70": "Community 70",
  "71": "Community 71",
  "72": "Community 72",
  "73": "Community 73",
  "74": "Community 74",
  "75": "Community 75",
  "76": "Community 76",
  "77": "Community 77",
  "78": "Community 78",
  "79": "Community 79",
  "80": "Community 80",
  "81": "Community 81",
  "82": "Community 82",
  "83": "Community 83",
  "84": "Community 84",
  "85": "Community 85",
  "87": "Community 87",
  "88": "Community 88",
  "89": "Community 89",
  "90": "Community 90",
  "91": "Community 91",
  "92": "Community 92"
}
